ccic/__init__.py
ccic/codecs.py
ccic/models.py
ccic/plotting.py
ccic/processing.py
ccic/tiler.py
ccic/bin/__init__.py
ccic/bin/extract_training_data.py
ccic/bin/process.py
ccic/bin/run_radar_only_retrieval.py
ccic/bin/test.py
ccic/bin/train.py
ccic/data/__init__.py
ccic/data/cloudsat.py
ccic/data/cpcir.py
ccic/data/dardar.py
ccic/data/gridsat.py
ccic/data/training_data.py
ccic/data/utils.py
ccic/files/ccic.mplstyle
ccic/validation/__init__.py
ccic/validation/input_data.py
ccic/validation/radars.py
ccic/validation/retrieval.py
ccic-0.1.dist-info/LICENSE
ccic-0.1.dist-info/METADATA
ccic-0.1.dist-info/WHEEL
ccic-0.1.dist-info/entry_points.txt
ccic-0.1.dist-info/top_level.txt
ccic-0.1.dist-info/RECORD
