Metadata-Version: 2.1
Name: ccic
Version: 0.1
Summary: Chalmers Cloud Ice Climatology
Home-page: https://github.com/see-geo/ccic
Author: Simon Pfreundschuh
Author-email: simon.pfreundschuh@chalmers.se
License: UNKNOWN
Project-URL: Source, https://github.com/see-geo/ccic/
Platform: UNKNOWN
Requires-Python: >=3.8
Requires-Dist: zarr
Requires-Dist: netCDF4
Requires-Dist: dask
Requires-Dist: beautifulsoup4
Requires-Dist: lxml
Requires-Dist: xarray
Provides-Extra: complete
Requires-Dist: metpy ; extra == 'complete'
Requires-Dist: numpy ; extra == 'complete'
Requires-Dist: quantnn >=0.0.5 ; extra == 'complete'
Requires-Dist: torch ==1.13.1 ; extra == 'complete'
Requires-Dist: torchvision ==0.14.1 ; extra == 'complete'
Requires-Dist: pytorch-lightning ; extra == 'complete'
Requires-Dist: pyresample ; extra == 'complete'
Requires-Dist: h5py ; extra == 'complete'
Requires-Dist: pansat ; extra == 'complete'
Requires-Dist: xarray ; extra == 'complete'
Requires-Dist: netCDF4 ; extra == 'complete'
Requires-Dist: dask ; extra == 'complete'
Requires-Dist: beautifulsoup4 ; extra == 'complete'
Requires-Dist: lxml ; extra == 'complete'
Requires-Dist: jupyter-book ; extra == 'complete'
